{
  "id": "61319",
  "title": "Baby Taylor Thanksgiving Cooking",
  "slug": "baby-taylor-thanksgiving-cooking",
  "description": "This is an online cooking game for Thanksgiving. You will have the opportunity to go into Taylors house to help them prepare for Thanksgiving. Firstly you will need to go to the supermarket and go shopping for ingredients and items to prepare the decorations. When you get home you will need to make the turkey first, from the ingredients to the baking.",
  "instructions": "Mouse click or tap to play",
  "url": "https://html5.gamemonetize.com/435zfhv6y544y6tyc75qobkf9w5nabqb/",
  "category": "Cooking",
  "categorySlug": "cooking",
  "tags": [
    "Food",
    "Shopping",
    "Super"
  ],
  "thumb": "https://img.gamemonetize.com/435zfhv6y544y6tyc75qobkf9w5nabqb/512x384.jpg",
  "width": 720,
  "height": 1280,
  "publisher": "babygames.com",
  "crawledAt": "2026-02-03T10:08:01.881Z"
}