{
  "classname": null,
  "name": null,
  "animation": {
    "classname": null,
    "name": "AnimationManager",
    "actionlist": [
      {
        "classname": null,
        "name": "in",
        "actionnodelist": [
          {
            "classname": null,
            "name": "close",
            "ActionTag": 22285262,
            "actionframelist": [
              {
                "classname": null,
                "name": null,
                "colorb": 255,
                "colorg": 255,
                "colorr": 255,
                "frameid": 0,
                "opacity": 255,
                "positionx": 141,
                "positiony": 190,
                "rotation": 0,
                "scalex": 0,
                "scaley": 0,
                "starttime": 0,
                "tweenParameter": [
                  0,
                  0,
                  1,
                  1
                ],
                "tweenType": 0,
                "visible": false
              },
              {
                "classname": null,
                "name": null,
                "colorb": 255,
                "colorg": 255,
                "colorr": 255,
                "frameid": 8,
                "opacity": 255,
                "positionx": 141,
                "positiony": 190,
                "rotation": 0,
                "scalex": 0,
                "scaley": 0,
                "starttime": 0,
                "tweenParameter": [
                  0,
                  0,
                  1,
                  1
                ],
                "tweenType": 0,
                "visible": false
              },
              {
                "classname": null,
                "name": null,
                "colorb": 255,
                "colorg": 255,
                "colorr": 255,
                "frameid": 11,
                "opacity": 255,
                "positionx": 141,
                "positiony": 190,
                "rotation": 0,
                "scalex": 1,
                "scaley": 1,
                "starttime": 0,
                "tweenParameter": [
                  0,
                  0,
                  1,
                  1
                ],
                "tweenType": 26,
                "visible": false
              }
            ]
          },
          {
            "classname": null,
            "name": "button1",
            "ActionTag": 60212448,
            "actionframelist": [
              {
                "classname": null,
                "name": null,
                "colorb": 255,
                "colorg": 255,
                "colorr": 255,
                "frameid": 0,
                "opacity": 255,
                "positionx": 0,
                "positiony": 52,
                "rotation": 0,
                "scalex": 0,
                "scaley": 0,
                "starttime": 0,
                "tweenParameter": [
                  0,
                  0,
                  1,
                  1
                ],
                "tweenType": 0,
                "visible": false
              },
              {
                "classname": null,
                "name": null,
                "colorb": 255,
                "colorg": 255,
                "colorr": 255,
                "frameid": 3,
                "opacity": 255,
                "positionx": 0,
                "positiony": 52,
                "rotation": 0,
                "scalex": 0,
                "scaley": 0,
                "starttime": 0,
                "tweenParameter": [
                  0,
                  0,
                  1,
                  1
                ],
                "tweenType": 0,
                "visible": false
              },
              {
                "classname": null,
                "name": null,
                "colorb": 255,
                "colorg": 255,
                "colorr": 255,
                "frameid": 6,
                "opacity": 255,
                "positionx": 0,
                "positiony": 52,
                "rotation": 0,
                "scalex": 1,
                "scaley": 1,
                "starttime": 0,
                "tweenParameter": [
                  0,
                  0,
                  1,
                  1
                ],
                "tweenType": 26,
                "visible": false
              }
            ]
          },
          {
            "classname": null,
            "name": "button2",
            "ActionTag": 46415143,
            "actionframelist": [
              {
                "classname": null,
                "name": null,
                "colorb": 255,
                "colorg": 255,
                "colorr": 255,
                "frameid": 0,
                "opacity": 255,
                "positionx": 0,
                "positiony": -33,
                "rotation": 0,
                "scalex": 0,
                "scaley": 0,
                "starttime": 0,
                "tweenParameter": [
                  0,
                  0,
                  1,
                  1
                ],
                "tweenType": 0,
                "visible": false
              },
              {
                "classname": null,
                "name": null,
                "colorb": 255,
                "colorg": 255,
                "colorr": 255,
                "frameid": 4,
                "opacity": 255,
                "positionx": 0,
                "positiony": -33,
                "rotation": 0,
                "scalex": 0,
                "scaley": 0,
                "starttime": 0,
                "tweenParameter": [
                  0,
                  0,
                  1,
                  1
                ],
                "tweenType": 0,
                "visible": false
              },
              {
                "classname": null,
                "name": null,
                "colorb": 255,
                "colorg": 255,
                "colorr": 255,
                "frameid": 7,
                "opacity": 255,
                "positionx": 0,
                "positiony": -33,
                "rotation": 0,
                "scalex": 1,
                "scaley": 1,
                "starttime": 0,
                "tweenParameter": [
                  0,
                  0,
                  1,
                  1
                ],
                "tweenType": 26,
                "visible": false
              }
            ]
          },
          {
            "classname": null,
            "name": "button3",
            "ActionTag": 57263252,
            "actionframelist": [
              {
                "classname": null,
                "name": null,
                "colorb": 255,
                "colorg": 255,
                "colorr": 255,
                "frameid": 0,
                "opacity": 255,
                "positionx": 0,
                "positiony": -119,
                "rotation": 0,
                "scalex": 0,
                "scaley": 0,
                "starttime": 0,
                "tweenParameter": [
                  0,
                  0,
                  1,
                  1
                ],
                "tweenType": 0,
                "visible": false
              },
              {
                "classname": null,
                "name": null,
                "colorb": 255,
                "colorg": 255,
                "colorr": 255,
                "frameid": 5,
                "opacity": 255,
                "positionx": 0,
                "positiony": -119,
                "rotation": 0,
                "scalex": 0,
                "scaley": 0,
                "starttime": 0,
                "tweenParameter": [
                  0,
                  0,
                  1,
                  1
                ],
                "tweenType": 0,
                "visible": false
              },
              {
                "classname": null,
                "name": null,
                "colorb": 255,
                "colorg": 255,
                "colorr": 255,
                "frameid": 8,
                "opacity": 255,
                "positionx": 0,
                "positiony": -119,
                "rotation": 0,
                "scalex": 1,
                "scaley": 1,
                "starttime": 0,
                "tweenParameter": [
                  0,
                  0,
                  1,
                  1
                ],
                "tweenType": 26,
                "visible": false
              }
            ]
          },
          {
            "classname": null,
            "name": "button4",
            "ActionTag": 42296564,
            "actionframelist": [
              {
                "classname": null,
                "name": null,
                "colorb": 255,
                "colorg": 255,
                "colorr": 255,
                "frameid": 0,
                "opacity": 255,
                "positionx": 0,
                "positiony": 138,
                "rotation": 0,
                "scalex": 0,
                "scaley": 0,
                "starttime": 0,
                "tweenParameter": [
                  0,
                  0,
                  1,
                  1
                ],
                "tweenType": 0,
                "visible": false
              },
              {
                "classname": null,
                "name": null,
                "colorb": 255,
                "colorg": 255,
                "colorr": 255,
                "frameid": 2,
                "opacity": 255,
                "positionx": 0,
                "positiony": 138,
                "rotation": 0,
                "scalex": 0,
                "scaley": 0,
                "starttime": 0,
                "tweenParameter": [
                  0,
                  0,
                  1,
                  1
                ],
                "tweenType": 0,
                "visible": false
              },
              {
                "classname": null,
                "name": null,
                "colorb": 255,
                "colorg": 255,
                "colorr": 255,
                "frameid": 5,
                "opacity": 255,
                "positionx": 0,
                "positiony": 138,
                "rotation": 0,
                "scalex": 1,
                "scaley": 1,
                "starttime": 0,
                "tweenParameter": [
                  0,
                  0,
                  1,
                  1
                ],
                "tweenType": 26,
                "visible": false
              }
            ]
          },
          {
            "classname": null,
            "name": "container",
            "ActionTag": 35962059,
            "actionframelist": [
              {
                "classname": null,
                "name": null,
                "colorb": 255,
                "colorg": 255,
                "colorr": 255,
                "frameid": 0,
                "opacity": 255,
                "positionx": 320,
                "positiony": 1200,
                "rotation": 0,
                "scalex": 1,
                "scaley": 1,
                "starttime": 0,
                "tweenParameter": [
                  0,
                  0,
                  1,
                  1
                ],
                "tweenType": 0,
                "visible": false
              },
              {
                "classname": null,
                "name": null,
                "colorb": 255,
                "colorg": 255,
                "colorr": 255,
                "frameid": 4,
                "opacity": 255,
                "positionx": 320,
                "positiony": 480,
                "rotation": 0,
                "scalex": 1,
                "scaley": 1,
                "starttime": 0,
                "tweenParameter": [
                  0,
                  0,
                  1,
                  1
                ],
                "tweenType": 17,
                "visible": false
              }
            ]
          }
        ],
        "loop": false,
        "unittime": 0.1
      },
      {
        "classname": null,
        "name": "out",
        "actionnodelist": [
          {
            "classname": null,
            "name": "container",
            "ActionTag": 35962059,
            "actionframelist": [
              {
                "classname": null,
                "name": null,
                "colorb": 255,
                "colorg": 255,
                "colorr": 255,
                "frameid": 0,
                "opacity": 255,
                "positionx": 320,
                "positiony": 480,
                "rotation": 0,
                "scalex": 1,
                "scaley": 1,
                "starttime": 0,
                "tweenParameter": [
                  0,
                  0,
                  1,
                  1
                ],
                "tweenType": 0,
                "visible": false
              },
              {
                "classname": null,
                "name": null,
                "colorb": 255,
                "colorg": 255,
                "colorr": 255,
                "frameid": 4,
                "opacity": 255,
                "positionx": 320,
                "positiony": 1200,
                "rotation": 0,
                "scalex": 1,
                "scaley": 1,
                "starttime": 0,
                "tweenParameter": [
                  0,
                  0,
                  1,
                  1
                ],
                "tweenType": 16,
                "visible": false
              }
            ]
          }
        ],
        "loop": false,
        "unittime": 0.1
      }
    ]
  },
  "dataScale": 1,
  "designHeight": 960,
  "designWidth": 640,
  "textures": [
    "ui_options0.plist"
  ],
  "texturesPng": [
    "ui_options0.png"
  ],
  "version": "1.6.0.0",
  "widgetTree": {
    "classname": "Panel",
    "name": null,
    "children": [
      {
        "classname": "ImageView",
        "name": null,
        "children": [
          {
            "classname": "Button",
            "name": null,
            "children": [
              {
                "classname": "LabelBMFont",
                "name": null,
                "children": [],
                "options": {
                  "__type": "LabelBMFontSurrogate:#EditorCommon.JsonModel.Component.GUI",
                  "classname": "LabelBMFont",
                  "name": "button1_text",
                  "ZOrder": 0,
                  "actiontag": 419111,
                  "anchorPointX": 0.5,
                  "anchorPointY": 0.6,
                  "classType": "CocoStudio.EngineAdapterWrap.CSLabelBMFont",
                  "colorB": 255,
                  "colorG": 255,
                  "colorR": 255,
                  "customProperty": "",
                  "flipX": false,
                  "flipY": false,
                  "height": 41,
                  "ignoreSize": true,
                  "layoutParameter": null,
                  "opacity": 255,
                  "positionPercentX": 0,
                  "positionPercentY": 0,
                  "positionType": 0,
                  "rotation": 0,
                  "scaleX": 1,
                  "scaleY": 1,
                  "sizePercentX": 0.127071828,
                  "sizePercentY": 0.5466667,
                  "sizeType": 0,
                  "tag": 910,
                  "touchAble": false,
                  "useMergedTexture": true,
                  "visible": true,
                  "width": 23,
                  "x": 0,
                  "y": 0,
                  "fileNameData": {
                    "path": "font_white_big3.fnt",
                    "plistFile": "",
                    "resourceType": 0
                  },
                  "text": "n"
                }
              }
            ],
            "options": {
              "__type": "ButtonSurrogate:#EditorCommon.JsonModel.Component.GUI",
              "classname": "Button",
              "name": "button1",
              "ZOrder": 0,
              "actiontag": 60212448,
              "anchorPointX": 0.5,
              "anchorPointY": 0.5,
              "classType": "CocoStudio.EngineAdapterWrap.CSButton",
              "colorB": 255,
              "colorG": 255,
              "colorR": 255,
              "customProperty": "",
              "flipX": false,
              "flipY": false,
              "height": 75,
              "ignoreSize": true,
              "layoutParameter": null,
              "opacity": 255,
              "positionPercentX": 0,
              "positionPercentY": 0.1336761,
              "positionType": 0,
              "rotation": 0,
              "scaleX": 1,
              "scaleY": 1,
              "sizePercentX": 0.603333354,
              "sizePercentY": 0.192802057,
              "sizeType": 0,
              "tag": 5,
              "touchAble": true,
              "useMergedTexture": true,
              "visible": true,
              "width": 181,
              "x": 0,
              "y": 52,
              "capInsetsHeight": 1,
              "capInsetsWidth": 1,
              "capInsetsX": 0,
              "capInsetsY": 0,
              "disabled": null,
              "disabledData": {
                "path": "standar_blue_button_press.png",
                "plistFile": "",
                "resourceType": 1
              },
              "fontName": "微软雅黑",
              "fontSize": 14,
              "fontType": 0,
              "normal": null,
              "normalData": {
                "path": "standar_blue_button.png",
                "plistFile": "",
                "resourceType": 1
              },
              "pressed": null,
              "pressedData": {
                "path": "standar_blue_button_press.png",
                "plistFile": "",
                "resourceType": 1
              },
              "scale9Enable": false,
              "scale9Height": 75,
              "scale9Width": 181,
              "text": "",
              "textColorB": 255,
              "textColorG": 255,
              "textColorR": 255
            }
          },
          {
            "classname": "Button",
            "name": null,
            "children": [
              {
                "classname": "LabelBMFont",
                "name": null,
                "children": [],
                "options": {
                  "__type": "LabelBMFontSurrogate:#EditorCommon.JsonModel.Component.GUI",
                  "classname": "LabelBMFont",
                  "name": "button2_text",
                  "ZOrder": 0,
                  "actiontag": 64106610,
                  "anchorPointX": 0.5,
                  "anchorPointY": 0.6,
                  "classType": "CocoStudio.EngineAdapterWrap.CSLabelBMFont",
                  "colorB": 255,
                  "colorG": 255,
                  "colorR": 255,
                  "customProperty": "",
                  "flipX": false,
                  "flipY": false,
                  "height": 41,
                  "ignoreSize": true,
                  "layoutParameter": null,
                  "opacity": 255,
                  "positionPercentX": 0,
                  "positionPercentY": 0,
                  "positionType": 0,
                  "rotation": 0,
                  "scaleX": 1,
                  "scaleY": 1,
                  "sizePercentX": 0.127071828,
                  "sizePercentY": 0.5466667,
                  "sizeType": 0,
                  "tag": 911,
                  "touchAble": false,
                  "useMergedTexture": true,
                  "visible": true,
                  "width": 23,
                  "x": 0,
                  "y": 0,
                  "fileNameData": {
                    "path": "font_white_big3.fnt",
                    "plistFile": "",
                    "resourceType": 0
                  },
                  "text": "n"
                }
              }
            ],
            "options": {
              "__type": "ButtonSurrogate:#EditorCommon.JsonModel.Component.GUI",
              "classname": "Button",
              "name": "button2",
              "ZOrder": 0,
              "actiontag": 46415143,
              "anchorPointX": 0.5,
              "anchorPointY": 0.5,
              "classType": "CocoStudio.EngineAdapterWrap.CSButton",
              "colorB": 255,
              "colorG": 255,
              "colorR": 255,
              "customProperty": "",
              "flipX": false,
              "flipY": false,
              "height": 75,
              "ignoreSize": true,
              "layoutParameter": null,
              "opacity": 255,
              "positionPercentX": 0,
              "positionPercentY": -0.08483291,
              "positionType": 0,
              "rotation": 0,
              "scaleX": 1,
              "scaleY": 1,
              "sizePercentX": 0.603333354,
              "sizePercentY": 0.192802057,
              "sizeType": 0,
              "tag": 6,
              "touchAble": true,
              "useMergedTexture": true,
              "visible": true,
              "width": 181,
              "x": 0,
              "y": -33,
              "capInsetsHeight": 1,
              "capInsetsWidth": 1,
              "capInsetsX": 0,
              "capInsetsY": 0,
              "disabled": null,
              "disabledData": {
                "path": "standar_blue_button_press.png",
                "plistFile": "",
                "resourceType": 1
              },
              "fontName": "微软雅黑",
              "fontSize": 14,
              "fontType": 0,
              "normal": null,
              "normalData": {
                "path": "standar_blue_button.png",
                "plistFile": "",
                "resourceType": 1
              },
              "pressed": null,
              "pressedData": {
                "path": "standar_blue_button_press.png",
                "plistFile": "",
                "resourceType": 1
              },
              "scale9Enable": false,
              "scale9Height": 75,
              "scale9Width": 181,
              "text": "",
              "textColorB": 255,
              "textColorG": 255,
              "textColorR": 255
            }
          },
          {
            "classname": "Button",
            "name": null,
            "children": [
              {
                "classname": "LabelBMFont",
                "name": null,
                "children": [],
                "options": {
                  "__type": "LabelBMFontSurrogate:#EditorCommon.JsonModel.Component.GUI",
                  "classname": "LabelBMFont",
                  "name": "button3_text",
                  "ZOrder": 0,
                  "actiontag": 6700043,
                  "anchorPointX": 0.5,
                  "anchorPointY": 0.6,
                  "classType": "CocoStudio.EngineAdapterWrap.CSLabelBMFont",
                  "colorB": 255,
                  "colorG": 255,
                  "colorR": 255,
                  "customProperty": "",
                  "flipX": false,
                  "flipY": false,
                  "height": 41,
                  "ignoreSize": true,
                  "layoutParameter": null,
                  "opacity": 255,
                  "positionPercentX": 0,
                  "positionPercentY": 0,
                  "positionType": 0,
                  "rotation": 0,
                  "scaleX": 1,
                  "scaleY": 1,
                  "sizePercentX": 0.127071828,
                  "sizePercentY": 0.5466667,
                  "sizeType": 0,
                  "tag": 912,
                  "touchAble": false,
                  "useMergedTexture": true,
                  "visible": true,
                  "width": 23,
                  "x": 0,
                  "y": 0,
                  "fileNameData": {
                    "path": "font_white_big3.fnt",
                    "plistFile": "",
                    "resourceType": 0
                  },
                  "text": "n"
                }
              }
            ],
            "options": {
              "__type": "ButtonSurrogate:#EditorCommon.JsonModel.Component.GUI",
              "classname": "Button",
              "name": "button3",
              "ZOrder": 0,
              "actiontag": 57263252,
              "anchorPointX": 0.5,
              "anchorPointY": 0.5,
              "classType": "CocoStudio.EngineAdapterWrap.CSButton",
              "colorB": 255,
              "colorG": 255,
              "colorR": 255,
              "customProperty": "",
              "flipX": false,
              "flipY": false,
              "height": 75,
              "ignoreSize": true,
              "layoutParameter": null,
              "opacity": 255,
              "positionPercentX": 0,
              "positionPercentY": -0.305912584,
              "positionType": 0,
              "rotation": 0,
              "scaleX": 1,
              "scaleY": 1,
              "sizePercentX": 0.603333354,
              "sizePercentY": 0.192802057,
              "sizeType": 0,
              "tag": 7,
              "touchAble": true,
              "useMergedTexture": true,
              "visible": true,
              "width": 181,
              "x": 0,
              "y": -119,
              "capInsetsHeight": 1,
              "capInsetsWidth": 1,
              "capInsetsX": 0,
              "capInsetsY": 0,
              "disabled": null,
              "disabledData": {
                "path": "no_button_press.png",
                "plistFile": "",
                "resourceType": 1
              },
              "fontName": "微软雅黑",
              "fontSize": 14,
              "fontType": 0,
              "normal": null,
              "normalData": {
                "path": "no_button.png",
                "plistFile": "",
                "resourceType": 1
              },
              "pressed": null,
              "pressedData": {
                "path": "no_button_press.png",
                "plistFile": "",
                "resourceType": 1
              },
              "scale9Enable": false,
              "scale9Height": 75,
              "scale9Width": 181,
              "text": "",
              "textColorB": 255,
              "textColorG": 255,
              "textColorR": 255
            }
          },
          {
            "classname": "Button",
            "name": null,
            "children": [
              {
                "classname": "LabelBMFont",
                "name": null,
                "children": [],
                "options": {
                  "__type": "LabelBMFontSurrogate:#EditorCommon.JsonModel.Component.GUI",
                  "classname": "LabelBMFont",
                  "name": "button4_text",
                  "ZOrder": 0,
                  "actiontag": 45124757,
                  "anchorPointX": 0.5,
                  "anchorPointY": 0.6,
                  "classType": "CocoStudio.EngineAdapterWrap.CSLabelBMFont",
                  "colorB": 255,
                  "colorG": 255,
                  "colorR": 255,
                  "customProperty": "",
                  "flipX": false,
                  "flipY": false,
                  "height": 41,
                  "ignoreSize": true,
                  "layoutParameter": null,
                  "opacity": 255,
                  "positionPercentX": 0,
                  "positionPercentY": 0,
                  "positionType": 0,
                  "rotation": 0,
                  "scaleX": 1,
                  "scaleY": 1,
                  "sizePercentX": 0.127071828,
                  "sizePercentY": 0.5466667,
                  "sizeType": 0,
                  "tag": 13169,
                  "touchAble": false,
                  "useMergedTexture": true,
                  "visible": true,
                  "width": 23,
                  "x": 0,
                  "y": 0,
                  "fileNameData": {
                    "path": "font_white_big3.fnt",
                    "plistFile": "",
                    "resourceType": 0
                  },
                  "text": "n"
                }
              }
            ],
            "options": {
              "__type": "ButtonSurrogate:#EditorCommon.JsonModel.Component.GUI",
              "classname": "Button",
              "name": "button4",
              "ZOrder": 0,
              "actiontag": 42296564,
              "anchorPointX": 0.5,
              "anchorPointY": 0.5,
              "classType": "CocoStudio.EngineAdapterWrap.CSButton",
              "colorB": 255,
              "colorG": 255,
              "colorR": 255,
              "customProperty": "",
              "flipX": false,
              "flipY": false,
              "height": 75,
              "ignoreSize": true,
              "layoutParameter": null,
              "opacity": 255,
              "positionPercentX": 0,
              "positionPercentY": 0.3547558,
              "positionType": 0,
              "rotation": 0,
              "scaleX": 1,
              "scaleY": 1,
              "sizePercentX": 0.603333354,
              "sizePercentY": 0.192802057,
              "sizeType": 0,
              "tag": 13168,
              "touchAble": true,
              "useMergedTexture": true,
              "visible": true,
              "width": 181,
              "x": 0,
              "y": 138,
              "capInsetsHeight": 1,
              "capInsetsWidth": 1,
              "capInsetsX": 0,
              "capInsetsY": 0,
              "disabled": null,
              "disabledData": {
                "path": "standar_blue_button_press.png",
                "plistFile": "",
                "resourceType": 1
              },
              "fontName": "微软雅黑",
              "fontSize": 14,
              "fontType": 0,
              "normal": null,
              "normalData": {
                "path": "standar_blue_button.png",
                "plistFile": "",
                "resourceType": 1
              },
              "pressed": null,
              "pressedData": {
                "path": "standar_blue_button_press.png",
                "plistFile": "",
                "resourceType": 1
              },
              "scale9Enable": false,
              "scale9Height": 75,
              "scale9Width": 181,
              "text": "",
              "textColorB": 255,
              "textColorG": 255,
              "textColorR": 255
            }
          },
          {
            "classname": "Button",
            "name": null,
            "children": [],
            "options": {
              "__type": "ButtonSurrogate:#EditorCommon.JsonModel.Component.GUI",
              "classname": "Button",
              "name": "close",
              "ZOrder": 0,
              "actiontag": 22285262,
              "anchorPointX": 0.5,
              "anchorPointY": 0.5,
              "classType": "CocoStudio.EngineAdapterWrap.CSButton",
              "colorB": 255,
              "colorG": 255,
              "colorR": 255,
              "customProperty": "",
              "flipX": false,
              "flipY": false,
              "height": 42,
              "ignoreSize": true,
              "layoutParameter": null,
              "opacity": 255,
              "positionPercentX": 0.47,
              "positionPercentY": 0.488431871,
              "positionType": 0,
              "rotation": 0,
              "scaleX": 1,
              "scaleY": 1,
              "sizePercentX": 0.143333331,
              "sizePercentY": 0.10796915,
              "sizeType": 0,
              "tag": 14377,
              "touchAble": true,
              "useMergedTexture": true,
              "visible": false,
              "width": 43,
              "x": 141,
              "y": 190,
              "capInsetsHeight": 1,
              "capInsetsWidth": 1,
              "capInsetsX": 0,
              "capInsetsY": 0,
              "disabled": null,
              "disabledData": {
                "path": "button_close_press.png",
                "plistFile": "",
                "resourceType": 1
              },
              "fontName": "微软雅黑",
              "fontSize": 14,
              "fontType": 0,
              "normal": null,
              "normalData": {
                "path": "button_close_normal.png",
                "plistFile": "",
                "resourceType": 1
              },
              "pressed": null,
              "pressedData": {
                "path": "button_close_press.png",
                "plistFile": "",
                "resourceType": 1
              },
              "scale9Enable": false,
              "scale9Height": 42,
              "scale9Width": 43,
              "text": "",
              "textColorB": 255,
              "textColorG": 255,
              "textColorR": 255
            }
          }
        ],
        "options": {
          "__type": "ImageViewSurrogate:#EditorCommon.JsonModel.Component.GUI",
          "classname": "ImageView",
          "name": "container",
          "ZOrder": 0,
          "actiontag": 35962059,
          "anchorPointX": 0.5,
          "anchorPointY": 0.5,
          "classType": "CocoStudio.EngineAdapterWrap.CSImageView",
          "colorB": 255,
          "colorG": 255,
          "colorR": 255,
          "customProperty": "",
          "flipX": false,
          "flipY": false,
          "height": 389,
          "ignoreSize": true,
          "layoutParameter": null,
          "opacity": 255,
          "positionPercentX": 0.5,
          "positionPercentY": 0.5,
          "positionType": 0,
          "rotation": 0,
          "scaleX": 1,
          "scaleY": 1,
          "sizePercentX": 0.46875,
          "sizePercentY": 0.405208319,
          "sizeType": 0,
          "tag": 4,
          "touchAble": false,
          "useMergedTexture": true,
          "visible": true,
          "width": 300,
          "x": 320,
          "y": 480,
          "capInsetsHeight": 1,
          "capInsetsWidth": 1,
          "capInsetsX": 0,
          "capInsetsY": 0,
          "fileName": null,
          "fileNameData": {
            "path": "container_options.png",
            "plistFile": "",
            "resourceType": 1
          },
          "scale9Enable": false,
          "scale9Height": 389,
          "scale9Width": 300
        }
      }
    ],
    "options": {
      "__type": "PanelSurrogate:#EditorCommon.JsonModel.Component.GUI",
      "classname": "Panel",
      "name": "panel",
      "ZOrder": 0,
      "actiontag": -1,
      "anchorPointX": 0,
      "anchorPointY": 0,
      "classType": "CocoStudio.EngineAdapterWrap.CSPanel",
      "colorB": 255,
      "colorG": 255,
      "colorR": 255,
      "customProperty": "",
      "flipX": false,
      "flipY": false,
      "height": 960,
      "ignoreSize": false,
      "layoutParameter": null,
      "opacity": 255,
      "positionPercentX": 0,
      "positionPercentY": 0,
      "positionType": 0,
      "rotation": 0,
      "scaleX": 1,
      "scaleY": 1,
      "sizePercentX": 1,
      "sizePercentY": 1,
      "sizeType": 0,
      "tag": 3,
      "touchAble": true,
      "useMergedTexture": true,
      "visible": true,
      "width": 640,
      "x": 0,
      "y": 0,
      "adaptScreen": false,
      "backGroundImage": null,
      "backGroundImageData": null,
      "backGroundScale9Enable": false,
      "bgColorB": 255,
      "bgColorG": 200,
      "bgColorOpacity": 0,
      "bgColorR": 150,
      "bgEndColorB": 255,
      "bgEndColorG": 200,
      "bgEndColorR": 150,
      "bgStartColorB": 255,
      "bgStartColorG": 255,
      "bgStartColorR": 255,
      "capInsetsHeight": 1,
      "capInsetsWidth": 1,
      "capInsetsX": 0,
      "capInsetsY": 0,
      "clipAble": false,
      "colorType": 1,
      "layoutType": 0,
      "vectorX": 0,
      "vectorY": -0.5
    }
  }
}