{
  "classname": null,
  "name": null,
  "animation": {
    "classname": null,
    "name": "AnimationManager",
    "actionlist": [
      {
        "classname": null,
        "name": "in",
        "actionnodelist": [
          {
            "classname": null,
            "name": "logo",
            "ActionTag": 66610962,
            "actionframelist": [
              {
                "classname": null,
                "name": null,
                "colorb": 255,
                "colorg": 255,
                "colorr": 255,
                "frameid": 0,
                "opacity": 255,
                "positionx": 320,
                "positiony": -200,
                "rotation": 0,
                "scalex": 1,
                "scaley": 1,
                "starttime": 0,
                "tweenParameter": [
                  0,
                  0,
                  1,
                  1
                ],
                "tweenType": 0,
                "visible": false
              },
              {
                "classname": null,
                "name": null,
                "colorb": 255,
                "colorg": 255,
                "colorr": 255,
                "frameid": 7,
                "opacity": 255,
                "positionx": 320,
                "positiony": 720,
                "rotation": 0,
                "scalex": 1,
                "scaley": 1,
                "starttime": 0,
                "tweenParameter": [
                  0,
                  0,
                  1,
                  1
                ],
                "tweenType": 17,
                "visible": false
              }
            ]
          },
          {
            "classname": null,
            "name": "bubble_4",
            "ActionTag": 529748,
            "actionframelist": [
              {
                "classname": null,
                "name": null,
                "colorb": 255,
                "colorg": 255,
                "colorr": 255,
                "frameid": 0,
                "opacity": 255,
                "positionx": 211,
                "positiony": -100,
                "rotation": 0,
                "scalex": 1,
                "scaley": 1,
                "starttime": 0,
                "tweenParameter": [],
                "tweenType": 0,
                "visible": false
              },
              {
                "classname": null,
                "name": null,
                "colorb": 255,
                "colorg": 255,
                "colorr": 255,
                "frameid": 3,
                "opacity": 255,
                "positionx": 211,
                "positiony": -100,
                "rotation": 0,
                "scalex": 1,
                "scaley": 1,
                "starttime": 0,
                "tweenParameter": [
                  0,
                  0,
                  1,
                  1
                ],
                "tweenType": 0,
                "visible": false
              },
              {
                "classname": null,
                "name": null,
                "colorb": 255,
                "colorg": 255,
                "colorr": 255,
                "frameid": 8,
                "opacity": 255,
                "positionx": 211,
                "positiony": 861,
                "rotation": 0,
                "scalex": 1,
                "scaley": 1,
                "starttime": 0,
                "tweenParameter": [
                  0,
                  0,
                  1,
                  1
                ],
                "tweenType": 17,
                "visible": false
              }
            ]
          },
          {
            "classname": null,
            "name": "bubble_3",
            "ActionTag": 50486238,
            "actionframelist": [
              {
                "classname": null,
                "name": null,
                "colorb": 255,
                "colorg": 255,
                "colorr": 255,
                "frameid": 0,
                "opacity": 255,
                "positionx": 582,
                "positiony": -100,
                "rotation": 0,
                "scalex": 1,
                "scaley": 1,
                "starttime": 0,
                "tweenParameter": [],
                "tweenType": 0,
                "visible": false
              },
              {
                "classname": null,
                "name": null,
                "colorb": 255,
                "colorg": 255,
                "colorr": 255,
                "frameid": 3,
                "opacity": 255,
                "positionx": 582,
                "positiony": -100,
                "rotation": 0,
                "scalex": 1,
                "scaley": 1,
                "starttime": 0,
                "tweenParameter": [
                  0,
                  0,
                  1,
                  1
                ],
                "tweenType": 0,
                "visible": false
              },
              {
                "classname": null,
                "name": null,
                "colorb": 255,
                "colorg": 255,
                "colorr": 255,
                "frameid": 8,
                "opacity": 255,
                "positionx": 582,
                "positiony": 607,
                "rotation": 0,
                "scalex": 1,
                "scaley": 1,
                "starttime": 0,
                "tweenParameter": [
                  0,
                  0,
                  1,
                  1
                ],
                "tweenType": 17,
                "visible": false
              }
            ]
          },
          {
            "classname": null,
            "name": "bubble_1",
            "ActionTag": 2620168,
            "actionframelist": [
              {
                "classname": null,
                "name": null,
                "colorb": 255,
                "colorg": 255,
                "colorr": 255,
                "frameid": 0,
                "opacity": 255,
                "positionx": 442,
                "positiony": -100,
                "rotation": 0,
                "scalex": 1,
                "scaley": 1,
                "starttime": 0,
                "tweenParameter": [],
                "tweenType": 0,
                "visible": false
              },
              {
                "classname": null,
                "name": null,
                "colorb": 255,
                "colorg": 255,
                "colorr": 255,
                "frameid": 4,
                "opacity": 255,
                "positionx": 442,
                "positiony": -100,
                "rotation": 0,
                "scalex": 1,
                "scaley": 1,
                "starttime": 0,
                "tweenParameter": [
                  0,
                  0,
                  1,
                  1
                ],
                "tweenType": 0,
                "visible": false
              },
              {
                "classname": null,
                "name": null,
                "colorb": 255,
                "colorg": 255,
                "colorr": 255,
                "frameid": 8,
                "opacity": 255,
                "positionx": 442,
                "positiony": 621,
                "rotation": 0,
                "scalex": 1,
                "scaley": 1,
                "starttime": 0,
                "tweenParameter": [
                  0,
                  0,
                  1,
                  1
                ],
                "tweenType": 17,
                "visible": false
              }
            ]
          },
          {
            "classname": null,
            "name": "bubble_6",
            "ActionTag": 32670228,
            "actionframelist": [
              {
                "classname": null,
                "name": null,
                "colorb": 255,
                "colorg": 255,
                "colorr": 255,
                "frameid": 0,
                "opacity": 255,
                "positionx": 208,
                "positiony": -100,
                "rotation": 0,
                "scalex": 1,
                "scaley": 1,
                "starttime": 0,
                "tweenParameter": [],
                "tweenType": 0,
                "visible": false
              },
              {
                "classname": null,
                "name": null,
                "colorb": 255,
                "colorg": 255,
                "colorr": 255,
                "frameid": 1,
                "opacity": 255,
                "positionx": 208,
                "positiony": -100,
                "rotation": 0,
                "scalex": 1,
                "scaley": 1,
                "starttime": 0,
                "tweenParameter": [
                  0,
                  0,
                  1,
                  1
                ],
                "tweenType": 0,
                "visible": false
              },
              {
                "classname": null,
                "name": null,
                "colorb": 255,
                "colorg": 255,
                "colorr": 255,
                "frameid": 8,
                "opacity": 255,
                "positionx": 208,
                "positiony": 574,
                "rotation": 0,
                "scalex": 1,
                "scaley": 1,
                "starttime": 0,
                "tweenParameter": [
                  0,
                  0,
                  1,
                  1
                ],
                "tweenType": 17,
                "visible": false
              }
            ]
          },
          {
            "classname": null,
            "name": "bubble_5",
            "ActionTag": 54841843,
            "actionframelist": [
              {
                "classname": null,
                "name": null,
                "colorb": 255,
                "colorg": 255,
                "colorr": 255,
                "frameid": 0,
                "opacity": 255,
                "positionx": 84,
                "positiony": -100,
                "rotation": 0,
                "scalex": 1,
                "scaley": 1,
                "starttime": 0,
                "tweenParameter": [],
                "tweenType": 0,
                "visible": false
              },
              {
                "classname": null,
                "name": null,
                "colorb": 255,
                "colorg": 255,
                "colorr": 255,
                "frameid": 3,
                "opacity": 255,
                "positionx": 84,
                "positiony": -100,
                "rotation": 0,
                "scalex": 1,
                "scaley": 1,
                "starttime": 0,
                "tweenParameter": [
                  0,
                  0,
                  1,
                  1
                ],
                "tweenType": 0,
                "visible": false
              },
              {
                "classname": null,
                "name": null,
                "colorb": 255,
                "colorg": 255,
                "colorr": 255,
                "frameid": 8,
                "opacity": 255,
                "positionx": 84,
                "positiony": 584,
                "rotation": 0,
                "scalex": 1,
                "scaley": 1,
                "starttime": 0,
                "tweenParameter": [
                  0,
                  0,
                  1,
                  1
                ],
                "tweenType": 17,
                "visible": false
              }
            ]
          },
          {
            "classname": null,
            "name": "bubble_2",
            "ActionTag": 16313428,
            "actionframelist": [
              {
                "classname": null,
                "name": null,
                "colorb": 255,
                "colorg": 255,
                "colorr": 255,
                "frameid": 0,
                "opacity": 255,
                "positionx": 31,
                "positiony": -100,
                "rotation": 0,
                "scalex": 1,
                "scaley": 1,
                "starttime": 0,
                "tweenParameter": [],
                "tweenType": 0,
                "visible": false
              },
              {
                "classname": null,
                "name": null,
                "colorb": 255,
                "colorg": 255,
                "colorr": 255,
                "frameid": 2,
                "opacity": 255,
                "positionx": 31,
                "positiony": -100,
                "rotation": 0,
                "scalex": 1,
                "scaley": 1,
                "starttime": 0,
                "tweenParameter": [
                  0,
                  0,
                  1,
                  1
                ],
                "tweenType": 0,
                "visible": false
              },
              {
                "classname": null,
                "name": null,
                "colorb": 255,
                "colorg": 255,
                "colorr": 255,
                "frameid": 7,
                "opacity": 255,
                "positionx": 31,
                "positiony": 684,
                "rotation": 0,
                "scalex": 1,
                "scaley": 1,
                "starttime": 0,
                "tweenParameter": [
                  0,
                  0,
                  1,
                  1
                ],
                "tweenType": 17,
                "visible": false
              }
            ]
          },
          {
            "classname": null,
            "name": "settings_button",
            "ActionTag": 421720,
            "actionframelist": [
              {
                "classname": null,
                "name": null,
                "colorb": 255,
                "colorg": 255,
                "colorr": 255,
                "frameid": 0,
                "opacity": 255,
                "positionx": 63.95392,
                "positiony": -82.8830261,
                "rotation": 0,
                "scalex": 1,
                "scaley": 1,
                "starttime": 0,
                "tweenParameter": [
                  0,
                  0,
                  1,
                  1
                ],
                "tweenType": 0,
                "visible": false
              },
              {
                "classname": null,
                "name": null,
                "colorb": 255,
                "colorg": 255,
                "colorr": 255,
                "frameid": 2,
                "opacity": 255,
                "positionx": 63.95392,
                "positiony": -82.88302,
                "rotation": 0,
                "scalex": 1,
                "scaley": 1,
                "starttime": 0,
                "tweenParameter": [
                  0,
                  0,
                  1,
                  1
                ],
                "tweenType": 0,
                "visible": false
              },
              {
                "classname": null,
                "name": null,
                "colorb": 255,
                "colorg": 255,
                "colorr": 255,
                "frameid": 7,
                "opacity": 255,
                "positionx": 63.95392,
                "positiony": 59.1170921,
                "rotation": 0,
                "scalex": 1,
                "scaley": 1,
                "starttime": 0,
                "tweenParameter": [
                  0,
                  0,
                  1,
                  1
                ],
                "tweenType": 26,
                "visible": false
              }
            ]
          },
          {
            "classname": null,
            "name": "play_button",
            "ActionTag": 3038051,
            "actionframelist": [
              {
                "classname": null,
                "name": null,
                "colorb": 255,
                "colorg": 255,
                "colorr": 255,
                "frameid": 0,
                "opacity": 255,
                "positionx": 320,
                "positiony": -142.497131,
                "rotation": 0,
                "scalex": 1,
                "scaley": 1,
                "starttime": 0,
                "tweenParameter": [
                  0,
                  0,
                  1,
                  1
                ],
                "tweenType": 0,
                "visible": false
              },
              {
                "classname": null,
                "name": null,
                "colorb": 255,
                "colorg": 255,
                "colorr": 255,
                "frameid": 3,
                "opacity": 255,
                "positionx": 320,
                "positiony": -142.497131,
                "rotation": 0,
                "scalex": 1,
                "scaley": 1,
                "starttime": 0,
                "tweenParameter": [
                  0,
                  0,
                  1,
                  1
                ],
                "tweenType": 0,
                "visible": false
              },
              {
                "classname": null,
                "name": null,
                "colorb": 255,
                "colorg": 255,
                "colorr": 255,
                "frameid": 8,
                "opacity": 255,
                "positionx": 320,
                "positiony": 129.5031,
                "rotation": 0,
                "scalex": 1,
                "scaley": 1,
                "starttime": 0,
                "tweenParameter": [
                  0,
                  0,
                  1,
                  1
                ],
                "tweenType": 26,
                "visible": false
              }
            ]
          }
        ],
        "loop": false,
        "unittime": 0.1
      },
      {
        "classname": null,
        "name": "out",
        "actionnodelist": [
          {
            "classname": null,
            "name": "bubble_1",
            "ActionTag": 2620168,
            "actionframelist": [
              {
                "classname": null,
                "name": null,
                "colorb": 255,
                "colorg": 255,
                "colorr": 255,
                "frameid": 0,
                "opacity": 255,
                "positionx": 442,
                "positiony": 621,
                "rotation": 0,
                "scalex": 1,
                "scaley": 1,
                "starttime": 0,
                "tweenParameter": [
                  0,
                  0,
                  1,
                  1
                ],
                "tweenType": 0,
                "visible": false
              },
              {
                "classname": null,
                "name": null,
                "colorb": 255,
                "colorg": 255,
                "colorr": 255,
                "frameid": 4,
                "opacity": 255,
                "positionx": 442,
                "positiony": 621,
                "rotation": 0,
                "scalex": 0,
                "scaley": 0,
                "starttime": 0,
                "tweenParameter": [
                  0,
                  0,
                  1,
                  1
                ],
                "tweenType": 25,
                "visible": false
              }
            ]
          },
          {
            "classname": null,
            "name": "bubble_2",
            "ActionTag": 16313428,
            "actionframelist": [
              {
                "classname": null,
                "name": null,
                "colorb": 255,
                "colorg": 255,
                "colorr": 255,
                "frameid": 0,
                "opacity": 255,
                "positionx": 31,
                "positiony": 684,
                "rotation": 0,
                "scalex": 1,
                "scaley": 1,
                "starttime": 0,
                "tweenParameter": [
                  0,
                  0,
                  1,
                  1
                ],
                "tweenType": 0,
                "visible": false
              },
              {
                "classname": null,
                "name": null,
                "colorb": 255,
                "colorg": 255,
                "colorr": 255,
                "frameid": 4,
                "opacity": 255,
                "positionx": 31,
                "positiony": 684,
                "rotation": 0,
                "scalex": 0,
                "scaley": 0,
                "starttime": 0,
                "tweenParameter": [
                  0,
                  0,
                  1,
                  1
                ],
                "tweenType": 25,
                "visible": false
              }
            ]
          },
          {
            "classname": null,
            "name": "bubble_3",
            "ActionTag": 50486238,
            "actionframelist": [
              {
                "classname": null,
                "name": null,
                "colorb": 255,
                "colorg": 255,
                "colorr": 255,
                "frameid": 0,
                "opacity": 255,
                "positionx": 582,
                "positiony": 607,
                "rotation": 0,
                "scalex": 1,
                "scaley": 1,
                "starttime": 0,
                "tweenParameter": [
                  0,
                  0,
                  1,
                  1
                ],
                "tweenType": 0,
                "visible": false
              },
              {
                "classname": null,
                "name": null,
                "colorb": 255,
                "colorg": 255,
                "colorr": 255,
                "frameid": 5,
                "opacity": 255,
                "positionx": 582,
                "positiony": 607,
                "rotation": 0,
                "scalex": 0,
                "scaley": 0,
                "starttime": 0,
                "tweenParameter": [
                  0,
                  0,
                  1,
                  1
                ],
                "tweenType": 25,
                "visible": false
              }
            ]
          },
          {
            "classname": null,
            "name": "bubble_4",
            "ActionTag": 529748,
            "actionframelist": [
              {
                "classname": null,
                "name": null,
                "colorb": 255,
                "colorg": 255,
                "colorr": 255,
                "frameid": 0,
                "opacity": 255,
                "positionx": 211,
                "positiony": 861,
                "rotation": 0,
                "scalex": 1,
                "scaley": 1,
                "starttime": 0,
                "tweenParameter": [],
                "tweenType": 0,
                "visible": false
              },
              {
                "classname": null,
                "name": null,
                "colorb": 255,
                "colorg": 255,
                "colorr": 255,
                "frameid": 2,
                "opacity": 255,
                "positionx": 211,
                "positiony": 861,
                "rotation": 0,
                "scalex": 1,
                "scaley": 1,
                "starttime": 0,
                "tweenParameter": [
                  0,
                  0,
                  1,
                  1
                ],
                "tweenType": 0,
                "visible": false
              },
              {
                "classname": null,
                "name": null,
                "colorb": 255,
                "colorg": 255,
                "colorr": 255,
                "frameid": 5,
                "opacity": 255,
                "positionx": 211,
                "positiony": 861,
                "rotation": 0,
                "scalex": 0,
                "scaley": 0,
                "starttime": 0,
                "tweenParameter": [
                  0,
                  0,
                  1,
                  1
                ],
                "tweenType": 25,
                "visible": false
              }
            ]
          },
          {
            "classname": null,
            "name": "bubble_5",
            "ActionTag": 54841843,
            "actionframelist": [
              {
                "classname": null,
                "name": null,
                "colorb": 255,
                "colorg": 255,
                "colorr": 255,
                "frameid": 0,
                "opacity": 255,
                "positionx": 84,
                "positiony": 584,
                "rotation": 0,
                "scalex": 1,
                "scaley": 1,
                "starttime": 0,
                "tweenParameter": [],
                "tweenType": 0,
                "visible": false
              },
              {
                "classname": null,
                "name": null,
                "colorb": 255,
                "colorg": 255,
                "colorr": 255,
                "frameid": 1,
                "opacity": 255,
                "positionx": 84,
                "positiony": 584,
                "rotation": 0,
                "scalex": 1,
                "scaley": 1,
                "starttime": 0,
                "tweenParameter": [
                  0,
                  0,
                  1,
                  1
                ],
                "tweenType": 0,
                "visible": false
              },
              {
                "classname": null,
                "name": null,
                "colorb": 255,
                "colorg": 255,
                "colorr": 255,
                "frameid": 6,
                "opacity": 255,
                "positionx": 84,
                "positiony": 584,
                "rotation": 0,
                "scalex": 0,
                "scaley": 0,
                "starttime": 0,
                "tweenParameter": [
                  0,
                  0,
                  1,
                  1
                ],
                "tweenType": 25,
                "visible": false
              }
            ]
          },
          {
            "classname": null,
            "name": "bubble_6",
            "ActionTag": 32670228,
            "actionframelist": [
              {
                "classname": null,
                "name": null,
                "colorb": 255,
                "colorg": 255,
                "colorr": 255,
                "frameid": 0,
                "opacity": 255,
                "positionx": 208,
                "positiony": 574,
                "rotation": 0,
                "scalex": 1,
                "scaley": 1,
                "starttime": 0,
                "tweenParameter": [],
                "tweenType": 0,
                "visible": false
              },
              {
                "classname": null,
                "name": null,
                "colorb": 255,
                "colorg": 255,
                "colorr": 255,
                "frameid": 2,
                "opacity": 255,
                "positionx": 208,
                "positiony": 574,
                "rotation": 0,
                "scalex": 1,
                "scaley": 1,
                "starttime": 0,
                "tweenParameter": [
                  0,
                  0,
                  1,
                  1
                ],
                "tweenType": 0,
                "visible": false
              },
              {
                "classname": null,
                "name": null,
                "colorb": 255,
                "colorg": 255,
                "colorr": 255,
                "frameid": 5,
                "opacity": 255,
                "positionx": 208,
                "positiony": 574,
                "rotation": 0,
                "scalex": 0,
                "scaley": 0,
                "starttime": 0,
                "tweenParameter": [
                  0,
                  0,
                  1,
                  1
                ],
                "tweenType": 25,
                "visible": false
              }
            ]
          },
          {
            "classname": null,
            "name": "logo",
            "ActionTag": 66610962,
            "actionframelist": [
              {
                "classname": null,
                "name": null,
                "colorb": 255,
                "colorg": 255,
                "colorr": 255,
                "frameid": 0,
                "opacity": 255,
                "positionx": 320,
                "positiony": 720,
                "rotation": 0,
                "scalex": 1,
                "scaley": 1,
                "starttime": 0,
                "tweenParameter": [
                  0,
                  0,
                  1,
                  1
                ],
                "tweenType": 0,
                "visible": false
              },
              {
                "classname": null,
                "name": null,
                "colorb": 255,
                "colorg": 255,
                "colorr": 255,
                "frameid": 4,
                "opacity": 255,
                "positionx": 320,
                "positiony": 720,
                "rotation": 0,
                "scalex": 0,
                "scaley": 0,
                "starttime": 0,
                "tweenParameter": [
                  0,
                  0,
                  1,
                  1
                ],
                "tweenType": 25,
                "visible": false
              }
            ]
          },
          {
            "classname": null,
            "name": "settings_button",
            "ActionTag": 421720,
            "actionframelist": [
              {
                "classname": null,
                "name": null,
                "colorb": 255,
                "colorg": 255,
                "colorr": 255,
                "frameid": 0,
                "opacity": 255,
                "positionx": 63.95392,
                "positiony": 59.1170921,
                "rotation": 0,
                "scalex": 1,
                "scaley": 1,
                "starttime": 0,
                "tweenParameter": [
                  0,
                  0,
                  1,
                  1
                ],
                "tweenType": 0,
                "visible": false
              },
              {
                "classname": null,
                "name": null,
                "colorb": 255,
                "colorg": 255,
                "colorr": 255,
                "frameid": 2,
                "opacity": 255,
                "positionx": 63.95392,
                "positiony": 59.1170921,
                "rotation": 0,
                "scalex": 1,
                "scaley": 1,
                "starttime": 0,
                "tweenParameter": [
                  0,
                  0,
                  1,
                  1
                ],
                "tweenType": 0,
                "visible": false
              },
              {
                "classname": null,
                "name": null,
                "colorb": 255,
                "colorg": 255,
                "colorr": 255,
                "frameid": 6,
                "opacity": 255,
                "positionx": 63.95392,
                "positiony": 59.1170921,
                "rotation": 0,
                "scalex": 0,
                "scaley": 0,
                "starttime": 0,
                "tweenParameter": [
                  0,
                  0,
                  1,
                  1
                ],
                "tweenType": 25,
                "visible": false
              }
            ]
          },
          {
            "classname": null,
            "name": "play_button",
            "ActionTag": 3038051,
            "actionframelist": [
              {
                "classname": null,
                "name": null,
                "colorb": 255,
                "colorg": 255,
                "colorr": 255,
                "frameid": 0,
                "opacity": 255,
                "positionx": 320,
                "positiony": 129.5031,
                "rotation": 0,
                "scalex": 1,
                "scaley": 1,
                "starttime": 0,
                "tweenParameter": [
                  0,
                  0,
                  1,
                  1
                ],
                "tweenType": 0,
                "visible": false
              },
              {
                "classname": null,
                "name": null,
                "colorb": 255,
                "colorg": 255,
                "colorr": 255,
                "frameid": 1,
                "opacity": 255,
                "positionx": 320,
                "positiony": 129.5031,
                "rotation": 0,
                "scalex": 1,
                "scaley": 1,
                "starttime": 0,
                "tweenParameter": [
                  0,
                  0,
                  1,
                  1
                ],
                "tweenType": 0,
                "visible": false
              },
              {
                "classname": null,
                "name": null,
                "colorb": 255,
                "colorg": 255,
                "colorr": 255,
                "frameid": 5,
                "opacity": 255,
                "positionx": 320,
                "positiony": 129.5031,
                "rotation": 0,
                "scalex": 0,
                "scaley": 0,
                "starttime": 0,
                "tweenParameter": [
                  0,
                  0,
                  1,
                  1
                ],
                "tweenType": 25,
                "visible": false
              }
            ]
          }
        ],
        "loop": false,
        "unittime": 0.1
      },
      {
        "classname": null,
        "name": "loop",
        "actionnodelist": [
          {
            "classname": null,
            "name": "bubble_1",
            "ActionTag": 2620168,
            "actionframelist": [
              {
                "classname": null,
                "name": null,
                "colorb": 255,
                "colorg": 255,
                "colorr": 255,
                "frameid": 0,
                "opacity": 255,
                "positionx": 442,
                "positiony": 621,
                "rotation": 0,
                "scalex": 1,
                "scaley": 1,
                "starttime": 0,
                "tweenParameter": [
                  0,
                  0,
                  1,
                  1
                ],
                "tweenType": 0,
                "visible": false
              },
              {
                "classname": null,
                "name": null,
                "colorb": 255,
                "colorg": 255,
                "colorr": 255,
                "frameid": 18,
                "opacity": 255,
                "positionx": 442,
                "positiony": 589,
                "rotation": 0,
                "scalex": 1,
                "scaley": 1,
                "starttime": 0,
                "tweenParameter": [],
                "tweenType": 0,
                "visible": false
              },
              {
                "classname": null,
                "name": null,
                "colorb": 255,
                "colorg": 255,
                "colorr": 255,
                "frameid": 40,
                "opacity": 255,
                "positionx": 442,
                "positiony": 621,
                "rotation": 0,
                "scalex": 1,
                "scaley": 1,
                "starttime": 0,
                "tweenParameter": [
                  0,
                  0,
                  1,
                  1
                ],
                "tweenType": 0,
                "visible": false
              }
            ]
          },
          {
            "classname": null,
            "name": "bubble_2",
            "ActionTag": 16313428,
            "actionframelist": [
              {
                "classname": null,
                "name": null,
                "colorb": 255,
                "colorg": 255,
                "colorr": 255,
                "frameid": 0,
                "opacity": 255,
                "positionx": 31,
                "positiony": 684,
                "rotation": 0,
                "scalex": 1,
                "scaley": 1,
                "starttime": 0,
                "tweenParameter": [
                  0,
                  0,
                  1,
                  1
                ],
                "tweenType": 0,
                "visible": false
              },
              {
                "classname": null,
                "name": null,
                "colorb": 255,
                "colorg": 255,
                "colorr": 255,
                "frameid": 18,
                "opacity": 255,
                "positionx": 31,
                "positiony": 669,
                "rotation": 0,
                "scalex": 1,
                "scaley": 1,
                "starttime": 0,
                "tweenParameter": [
                  0,
                  0,
                  1,
                  1
                ],
                "tweenType": 0,
                "visible": false
              },
              {
                "classname": null,
                "name": null,
                "colorb": 255,
                "colorg": 255,
                "colorr": 255,
                "frameid": 40,
                "opacity": 255,
                "positionx": 31,
                "positiony": 684,
                "rotation": 0,
                "scalex": 1,
                "scaley": 1,
                "starttime": 0,
                "tweenParameter": [
                  0,
                  0,
                  1,
                  1
                ],
                "tweenType": 0,
                "visible": false
              }
            ]
          },
          {
            "classname": null,
            "name": "bubble_3",
            "ActionTag": 50486238,
            "actionframelist": [
              {
                "classname": null,
                "name": null,
                "colorb": 255,
                "colorg": 255,
                "colorr": 255,
                "frameid": 0,
                "opacity": 255,
                "positionx": 582,
                "positiony": 607,
                "rotation": 0,
                "scalex": 1,
                "scaley": 1,
                "starttime": 0,
                "tweenParameter": [
                  0,
                  0,
                  1,
                  1
                ],
                "tweenType": 0,
                "visible": false
              },
              {
                "classname": null,
                "name": null,
                "colorb": 255,
                "colorg": 255,
                "colorr": 255,
                "frameid": 20,
                "opacity": 255,
                "positionx": 582,
                "positiony": 624,
                "rotation": 0,
                "scalex": 1,
                "scaley": 1,
                "starttime": 0,
                "tweenParameter": [
                  0,
                  0,
                  1,
                  1
                ],
                "tweenType": 0,
                "visible": false
              },
              {
                "classname": null,
                "name": null,
                "colorb": 255,
                "colorg": 255,
                "colorr": 255,
                "frameid": 40,
                "opacity": 255,
                "positionx": 582,
                "positiony": 607,
                "rotation": 0,
                "scalex": 1,
                "scaley": 1,
                "starttime": 0,
                "tweenParameter": [
                  0,
                  0,
                  1,
                  1
                ],
                "tweenType": 0,
                "visible": false
              }
            ]
          },
          {
            "classname": null,
            "name": "bubble_4",
            "ActionTag": 529748,
            "actionframelist": [
              {
                "classname": null,
                "name": null,
                "colorb": 255,
                "colorg": 255,
                "colorr": 255,
                "frameid": 0,
                "opacity": 255,
                "positionx": 211,
                "positiony": 861,
                "rotation": 0,
                "scalex": 1,
                "scaley": 1,
                "starttime": 0,
                "tweenParameter": [
                  0,
                  0,
                  1,
                  1
                ],
                "tweenType": 0,
                "visible": false
              },
              {
                "classname": null,
                "name": null,
                "colorb": 255,
                "colorg": 255,
                "colorr": 255,
                "frameid": 14,
                "opacity": 255,
                "positionx": 211,
                "positiony": 867,
                "rotation": 0,
                "scalex": 1,
                "scaley": 1,
                "starttime": 0,
                "tweenParameter": [
                  0,
                  0,
                  1,
                  1
                ],
                "tweenType": 0,
                "visible": false
              },
              {
                "classname": null,
                "name": null,
                "colorb": 255,
                "colorg": 255,
                "colorr": 255,
                "frameid": 25,
                "opacity": 255,
                "positionx": 211,
                "positiony": 841,
                "rotation": 0,
                "scalex": 1,
                "scaley": 1,
                "starttime": 0,
                "tweenParameter": [
                  0,
                  0,
                  1,
                  1
                ],
                "tweenType": 0,
                "visible": false
              },
              {
                "classname": null,
                "name": null,
                "colorb": 255,
                "colorg": 255,
                "colorr": 255,
                "frameid": 40,
                "opacity": 255,
                "positionx": 211,
                "positiony": 861,
                "rotation": 0,
                "scalex": 1,
                "scaley": 1,
                "starttime": 0,
                "tweenParameter": [
                  0,
                  0,
                  1,
                  1
                ],
                "tweenType": 0,
                "visible": false
              }
            ]
          },
          {
            "classname": null,
            "name": "bubble_5",
            "ActionTag": 54841843,
            "actionframelist": [
              {
                "classname": null,
                "name": null,
                "colorb": 255,
                "colorg": 255,
                "colorr": 255,
                "frameid": 0,
                "opacity": 255,
                "positionx": 84,
                "positiony": 584,
                "rotation": 0,
                "scalex": 1,
                "scaley": 1,
                "starttime": 0,
                "tweenParameter": [
                  0,
                  0,
                  1,
                  1
                ],
                "tweenType": 0,
                "visible": false
              },
              {
                "classname": null,
                "name": null,
                "colorb": 255,
                "colorg": 255,
                "colorr": 255,
                "frameid": 18,
                "opacity": 255,
                "positionx": 84,
                "positiony": 595,
                "rotation": 0,
                "scalex": 1,
                "scaley": 1,
                "starttime": 0,
                "tweenParameter": [
                  0,
                  0,
                  1,
                  1
                ],
                "tweenType": 0,
                "visible": false
              },
              {
                "classname": null,
                "name": null,
                "colorb": 255,
                "colorg": 255,
                "colorr": 255,
                "frameid": 40,
                "opacity": 255,
                "positionx": 84,
                "positiony": 584,
                "rotation": 0,
                "scalex": 1,
                "scaley": 1,
                "starttime": 0,
                "tweenParameter": [
                  0,
                  0,
                  1,
                  1
                ],
                "tweenType": 0,
                "visible": false
              }
            ]
          },
          {
            "classname": null,
            "name": "bubble_6",
            "ActionTag": 32670228,
            "actionframelist": [
              {
                "classname": null,
                "name": null,
                "colorb": 255,
                "colorg": 255,
                "colorr": 255,
                "frameid": 0,
                "opacity": 255,
                "positionx": 208,
                "positiony": 574,
                "rotation": 0,
                "scalex": 1,
                "scaley": 1,
                "starttime": 0,
                "tweenParameter": [
                  0,
                  0,
                  1,
                  1
                ],
                "tweenType": 0,
                "visible": false
              },
              {
                "classname": null,
                "name": null,
                "colorb": 255,
                "colorg": 255,
                "colorr": 255,
                "frameid": 13,
                "opacity": 255,
                "positionx": 208,
                "positiony": 556,
                "rotation": 0,
                "scalex": 1,
                "scaley": 1,
                "starttime": 0,
                "tweenParameter": [
                  0,
                  0,
                  1,
                  1
                ],
                "tweenType": 0,
                "visible": false
              },
              {
                "classname": null,
                "name": null,
                "colorb": 255,
                "colorg": 255,
                "colorr": 255,
                "frameid": 29,
                "opacity": 255,
                "positionx": 208,
                "positiony": 582,
                "rotation": 0,
                "scalex": 1,
                "scaley": 1,
                "starttime": 0,
                "tweenParameter": [
                  0,
                  0,
                  1,
                  1
                ],
                "tweenType": 0,
                "visible": false
              },
              {
                "classname": null,
                "name": null,
                "colorb": 255,
                "colorg": 255,
                "colorr": 255,
                "frameid": 40,
                "opacity": 255,
                "positionx": 208,
                "positiony": 574,
                "rotation": 0,
                "scalex": 1,
                "scaley": 1,
                "starttime": 0,
                "tweenParameter": [
                  0,
                  0,
                  1,
                  1
                ],
                "tweenType": 0,
                "visible": false
              }
            ]
          },
          {
            "classname": null,
            "name": "logo",
            "ActionTag": 66610962,
            "actionframelist": [
              {
                "classname": null,
                "name": null,
                "colorb": 255,
                "colorg": 255,
                "colorr": 255,
                "frameid": 0,
                "opacity": 255,
                "positionx": 320,
                "positiony": 720,
                "rotation": 0,
                "scalex": 1,
                "scaley": 1,
                "starttime": 0,
                "tweenParameter": [
                  0,
                  0,
                  1,
                  1
                ],
                "tweenType": 0,
                "visible": false
              },
              {
                "classname": null,
                "name": null,
                "colorb": 255,
                "colorg": 255,
                "colorr": 255,
                "frameid": 17,
                "opacity": 255,
                "positionx": 320,
                "positiony": 708,
                "rotation": 0,
                "scalex": 1,
                "scaley": 1,
                "starttime": 0,
                "tweenParameter": [
                  0,
                  0,
                  1,
                  1
                ],
                "tweenType": 0,
                "visible": false
              },
              {
                "classname": null,
                "name": null,
                "colorb": 255,
                "colorg": 255,
                "colorr": 255,
                "frameid": 40,
                "opacity": 255,
                "positionx": 320,
                "positiony": 720,
                "rotation": 0,
                "scalex": 1,
                "scaley": 1,
                "starttime": 0,
                "tweenParameter": [
                  0,
                  0,
                  1,
                  1
                ],
                "tweenType": 0,
                "visible": false
              }
            ]
          },
          {
            "classname": null,
            "name": "settings_button",
            "ActionTag": 421720,
            "actionframelist": [
              {
                "classname": null,
                "name": null,
                "colorb": 255,
                "colorg": 255,
                "colorr": 255,
                "frameid": 0,
                "opacity": 255,
                "positionx": 63.95392,
                "positiony": 59.1170921,
                "rotation": 0,
                "scalex": 1,
                "scaley": 1,
                "starttime": 0,
                "tweenParameter": [
                  0,
                  0,
                  1,
                  1
                ],
                "tweenType": 0,
                "visible": false
              }
            ]
          },
          {
            "classname": null,
            "name": "play_button",
            "ActionTag": 3038051,
            "actionframelist": [
              {
                "classname": null,
                "name": null,
                "colorb": 255,
                "colorg": 255,
                "colorr": 255,
                "frameid": 0,
                "opacity": 255,
                "positionx": 320,
                "positiony": 129.5031,
                "rotation": 0,
                "scalex": 1,
                "scaley": 1,
                "starttime": 0,
                "tweenParameter": [
                  0,
                  0,
                  1,
                  1
                ],
                "tweenType": 0,
                "visible": false
              },
              {
                "classname": null,
                "name": null,
                "colorb": 255,
                "colorg": 255,
                "colorr": 255,
                "frameid": 5,
                "opacity": 255,
                "positionx": 320,
                "positiony": 129.5031,
                "rotation": 0,
                "scalex": 1,
                "scaley": 1,
                "starttime": 0,
                "tweenParameter": [
                  0,
                  0,
                  1,
                  1
                ],
                "tweenType": 0,
                "visible": false
              },
              {
                "classname": null,
                "name": null,
                "colorb": 255,
                "colorg": 255,
                "colorr": 255,
                "frameid": 7,
                "opacity": 255,
                "positionx": 320,
                "positiony": 129.5031,
                "rotation": 0,
                "scalex": 1,
                "scaley": 0.799999952,
                "starttime": 0,
                "tweenParameter": [
                  0,
                  0,
                  1,
                  1
                ],
                "tweenType": 0,
                "visible": false
              },
              {
                "classname": null,
                "name": null,
                "colorb": 255,
                "colorg": 255,
                "colorr": 255,
                "frameid": 9,
                "opacity": 255,
                "positionx": 320,
                "positiony": 129.5031,
                "rotation": 0,
                "scalex": 1,
                "scaley": 1.1,
                "starttime": 0,
                "tweenParameter": [
                  0,
                  0,
                  1,
                  1
                ],
                "tweenType": 26,
                "visible": false
              },
              {
                "classname": null,
                "name": null,
                "colorb": 255,
                "colorg": 255,
                "colorr": 255,
                "frameid": 11,
                "opacity": 255,
                "positionx": 320,
                "positiony": 129.5031,
                "rotation": 0,
                "scalex": 1,
                "scaley": 1,
                "starttime": 0,
                "tweenParameter": [
                  0,
                  0,
                  1,
                  1
                ],
                "tweenType": 0,
                "visible": false
              },
              {
                "classname": null,
                "name": null,
                "colorb": 255,
                "colorg": 255,
                "colorr": 255,
                "frameid": 19,
                "opacity": 255,
                "positionx": 320,
                "positiony": 129.5031,
                "rotation": 0,
                "scalex": 1,
                "scaley": 1,
                "starttime": 0,
                "tweenParameter": [
                  0,
                  0,
                  1,
                  1
                ],
                "tweenType": 0,
                "visible": false
              },
              {
                "classname": null,
                "name": null,
                "colorb": 255,
                "colorg": 255,
                "colorr": 255,
                "frameid": 21,
                "opacity": 255,
                "positionx": 320,
                "positiony": 129.5031,
                "rotation": 0,
                "scalex": 1,
                "scaley": 0.799999952,
                "starttime": 0,
                "tweenParameter": [
                  0,
                  0,
                  1,
                  1
                ],
                "tweenType": 0,
                "visible": false
              },
              {
                "classname": null,
                "name": null,
                "colorb": 255,
                "colorg": 255,
                "colorr": 255,
                "frameid": 23,
                "opacity": 255,
                "positionx": 320,
                "positiony": 129.5031,
                "rotation": 0,
                "scalex": 1,
                "scaley": 1.1,
                "starttime": 0,
                "tweenParameter": [
                  0,
                  0,
                  1,
                  1
                ],
                "tweenType": 26,
                "visible": false
              },
              {
                "classname": null,
                "name": null,
                "colorb": 255,
                "colorg": 255,
                "colorr": 255,
                "frameid": 25,
                "opacity": 255,
                "positionx": 320,
                "positiony": 129.5031,
                "rotation": 0,
                "scalex": 1,
                "scaley": 1,
                "starttime": 0,
                "tweenParameter": [
                  0,
                  0,
                  1,
                  1
                ],
                "tweenType": 0,
                "visible": false
              },
              {
                "classname": null,
                "name": null,
                "colorb": 255,
                "colorg": 255,
                "colorr": 255,
                "frameid": 33,
                "opacity": 255,
                "positionx": 320,
                "positiony": 129.5031,
                "rotation": 0,
                "scalex": 1,
                "scaley": 1,
                "starttime": 0,
                "tweenParameter": [
                  0,
                  0,
                  1,
                  1
                ],
                "tweenType": 0,
                "visible": false
              },
              {
                "classname": null,
                "name": null,
                "colorb": 255,
                "colorg": 255,
                "colorr": 255,
                "frameid": 35,
                "opacity": 255,
                "positionx": 320,
                "positiony": 129.5031,
                "rotation": 0,
                "scalex": 1,
                "scaley": 0.799999952,
                "starttime": 0,
                "tweenParameter": [
                  0,
                  0,
                  1,
                  1
                ],
                "tweenType": 0,
                "visible": false
              },
              {
                "classname": null,
                "name": null,
                "colorb": 255,
                "colorg": 255,
                "colorr": 255,
                "frameid": 37,
                "opacity": 255,
                "positionx": 320,
                "positiony": 129.5031,
                "rotation": 0,
                "scalex": 1,
                "scaley": 1.1,
                "starttime": 0,
                "tweenParameter": [
                  0,
                  0,
                  1,
                  1
                ],
                "tweenType": 26,
                "visible": false
              },
              {
                "classname": null,
                "name": null,
                "colorb": 255,
                "colorg": 255,
                "colorr": 255,
                "frameid": 39,
                "opacity": 255,
                "positionx": 320,
                "positiony": 129.5031,
                "rotation": 0,
                "scalex": 1,
                "scaley": 1,
                "starttime": 0,
                "tweenParameter": [
                  0,
                  0,
                  1,
                  1
                ],
                "tweenType": 0,
                "visible": false
              }
            ]
          }
        ],
        "loop": true,
        "unittime": 0.1
      }
    ]
  },
  "dataScale": 1,
  "designHeight": 960,
  "designWidth": 640,
  "textures": [
    "ui_main_menu0.plist"
  ],
  "texturesPng": [
    "ui_main_menu0.png"
  ],
  "version": "1.6.0.0",
  "widgetTree": {
    "classname": "Panel",
    "name": null,
    "children": [
      {
        "classname": "ImageView",
        "name": null,
        "children": [],
        "options": {
          "__type": "ImageViewSurrogate:#EditorCommon.JsonModel.Component.GUI",
          "classname": "ImageView",
          "name": "bubble_6",
          "ZOrder": 0,
          "actiontag": 32670228,
          "anchorPointX": 0.5,
          "anchorPointY": 0.5,
          "classType": "CocoStudio.EngineAdapterWrap.CSImageView",
          "colorB": 255,
          "colorG": 255,
          "colorR": 255,
          "customProperty": "",
          "flipX": false,
          "flipY": false,
          "height": 52,
          "ignoreSize": true,
          "layoutParameter": null,
          "opacity": 255,
          "positionPercentX": 0.325,
          "positionPercentY": 0.597916663,
          "positionType": 0,
          "rotation": 0,
          "scaleX": 1,
          "scaleY": 1,
          "sizePercentX": 0.08125,
          "sizePercentY": 0.0541666672,
          "sizeType": 0,
          "tag": 16117,
          "touchAble": false,
          "useMergedTexture": true,
          "visible": true,
          "width": 52,
          "x": 208,
          "y": 574,
          "capInsetsHeight": 1,
          "capInsetsWidth": 1,
          "capInsetsX": 0,
          "capInsetsY": 0,
          "fileName": null,
          "fileNameData": {
            "path": "bubble1.png",
            "plistFile": "",
            "resourceType": 1
          },
          "scale9Enable": false,
          "scale9Height": 52,
          "scale9Width": 52
        }
      },
      {
        "classname": "ImageView",
        "name": null,
        "children": [],
        "options": {
          "__type": "ImageViewSurrogate:#EditorCommon.JsonModel.Component.GUI",
          "classname": "ImageView",
          "name": "bubble_5",
          "ZOrder": 0,
          "actiontag": 54841843,
          "anchorPointX": 0.5,
          "anchorPointY": 0.5,
          "classType": "CocoStudio.EngineAdapterWrap.CSImageView",
          "colorB": 255,
          "colorG": 255,
          "colorR": 255,
          "customProperty": "",
          "flipX": false,
          "flipY": false,
          "height": 52,
          "ignoreSize": true,
          "layoutParameter": null,
          "opacity": 255,
          "positionPercentX": 0.13125,
          "positionPercentY": 0.608333349,
          "positionType": 0,
          "rotation": 0,
          "scaleX": 1,
          "scaleY": 1,
          "sizePercentX": 0.08125,
          "sizePercentY": 0.0541666672,
          "sizeType": 0,
          "tag": 16116,
          "touchAble": false,
          "useMergedTexture": true,
          "visible": true,
          "width": 52,
          "x": 84,
          "y": 584,
          "capInsetsHeight": 1,
          "capInsetsWidth": 1,
          "capInsetsX": 0,
          "capInsetsY": 0,
          "fileName": null,
          "fileNameData": {
            "path": "bubble3.png",
            "plistFile": "",
            "resourceType": 1
          },
          "scale9Enable": false,
          "scale9Height": 52,
          "scale9Width": 52
        }
      },
      {
        "classname": "ImageView",
        "name": null,
        "children": [],
        "options": {
          "__type": "ImageViewSurrogate:#EditorCommon.JsonModel.Component.GUI",
          "classname": "ImageView",
          "name": "bubble_4",
          "ZOrder": 0,
          "actiontag": 529748,
          "anchorPointX": 0.5,
          "anchorPointY": 0.5,
          "classType": "CocoStudio.EngineAdapterWrap.CSImageView",
          "colorB": 255,
          "colorG": 255,
          "colorR": 255,
          "customProperty": "",
          "flipX": false,
          "flipY": false,
          "height": 52,
          "ignoreSize": true,
          "layoutParameter": null,
          "opacity": 255,
          "positionPercentX": 0.3296875,
          "positionPercentY": 0.896875,
          "positionType": 0,
          "rotation": 0,
          "scaleX": 1,
          "scaleY": 1,
          "sizePercentX": 0.08125,
          "sizePercentY": 0.0541666672,
          "sizeType": 0,
          "tag": 16115,
          "touchAble": false,
          "useMergedTexture": true,
          "visible": true,
          "width": 52,
          "x": 211,
          "y": 861,
          "capInsetsHeight": 1,
          "capInsetsWidth": 1,
          "capInsetsX": 0,
          "capInsetsY": 0,
          "fileName": null,
          "fileNameData": {
            "path": "bubble2.png",
            "plistFile": "",
            "resourceType": 1
          },
          "scale9Enable": false,
          "scale9Height": 52,
          "scale9Width": 52
        }
      },
      {
        "classname": "ImageView",
        "name": null,
        "children": [],
        "options": {
          "__type": "ImageViewSurrogate:#EditorCommon.JsonModel.Component.GUI",
          "classname": "ImageView",
          "name": "bubble_3",
          "ZOrder": 0,
          "actiontag": 50486238,
          "anchorPointX": 0.5,
          "anchorPointY": 0.5,
          "classType": "CocoStudio.EngineAdapterWrap.CSImageView",
          "colorB": 255,
          "colorG": 255,
          "colorR": 255,
          "customProperty": "",
          "flipX": false,
          "flipY": false,
          "height": 52,
          "ignoreSize": true,
          "layoutParameter": null,
          "opacity": 255,
          "positionPercentX": 0.909375,
          "positionPercentY": 0.6322917,
          "positionType": 0,
          "rotation": 0,
          "scaleX": 1,
          "scaleY": 1,
          "sizePercentX": 0.08125,
          "sizePercentY": 0.0541666672,
          "sizeType": 0,
          "tag": 16114,
          "touchAble": false,
          "useMergedTexture": true,
          "visible": true,
          "width": 52,
          "x": 582,
          "y": 607,
          "capInsetsHeight": 1,
          "capInsetsWidth": 1,
          "capInsetsX": 0,
          "capInsetsY": 0,
          "fileName": null,
          "fileNameData": {
            "path": "bubble6.png",
            "plistFile": "",
            "resourceType": 1
          },
          "scale9Enable": false,
          "scale9Height": 52,
          "scale9Width": 52
        }
      },
      {
        "classname": "ImageView",
        "name": null,
        "children": [],
        "options": {
          "__type": "ImageViewSurrogate:#EditorCommon.JsonModel.Component.GUI",
          "classname": "ImageView",
          "name": "bubble_2",
          "ZOrder": 0,
          "actiontag": 16313428,
          "anchorPointX": 0.5,
          "anchorPointY": 0.5,
          "classType": "CocoStudio.EngineAdapterWrap.CSImageView",
          "colorB": 255,
          "colorG": 255,
          "colorR": 255,
          "customProperty": "",
          "flipX": false,
          "flipY": false,
          "height": 52,
          "ignoreSize": true,
          "layoutParameter": null,
          "opacity": 255,
          "positionPercentX": 0.0484375,
          "positionPercentY": 0.7125,
          "positionType": 0,
          "rotation": 0,
          "scaleX": 1,
          "scaleY": 1,
          "sizePercentX": 0.08125,
          "sizePercentY": 0.0541666672,
          "sizeType": 0,
          "tag": 16113,
          "touchAble": false,
          "useMergedTexture": true,
          "visible": true,
          "width": 52,
          "x": 31,
          "y": 684,
          "capInsetsHeight": 1,
          "capInsetsWidth": 1,
          "capInsetsX": 0,
          "capInsetsY": 0,
          "fileName": null,
          "fileNameData": {
            "path": "bubble4.png",
            "plistFile": "",
            "resourceType": 1
          },
          "scale9Enable": false,
          "scale9Height": 52,
          "scale9Width": 52
        }
      },
      {
        "classname": "ImageView",
        "name": null,
        "children": [],
        "options": {
          "__type": "ImageViewSurrogate:#EditorCommon.JsonModel.Component.GUI",
          "classname": "ImageView",
          "name": "bubble_1",
          "ZOrder": 0,
          "actiontag": 2620168,
          "anchorPointX": 0.5,
          "anchorPointY": 0.5,
          "classType": "CocoStudio.EngineAdapterWrap.CSImageView",
          "colorB": 255,
          "colorG": 255,
          "colorR": 255,
          "customProperty": "",
          "flipX": false,
          "flipY": false,
          "height": 52,
          "ignoreSize": true,
          "layoutParameter": null,
          "opacity": 255,
          "positionPercentX": 0.690625,
          "positionPercentY": 0.646875,
          "positionType": 0,
          "rotation": 0,
          "scaleX": 1,
          "scaleY": 1,
          "sizePercentX": 0.08125,
          "sizePercentY": 0.0541666672,
          "sizeType": 0,
          "tag": 16112,
          "touchAble": false,
          "useMergedTexture": true,
          "visible": true,
          "width": 52,
          "x": 442,
          "y": 621,
          "capInsetsHeight": 1,
          "capInsetsWidth": 1,
          "capInsetsX": 0,
          "capInsetsY": 0,
          "fileName": null,
          "fileNameData": {
            "path": "bubble5.png",
            "plistFile": "",
            "resourceType": 1
          },
          "scale9Enable": false,
          "scale9Height": 52,
          "scale9Width": 52
        }
      },
      {
        "classname": "ImageView",
        "name": null,
        "children": [],
        "options": {
          "__type": "ImageViewSurrogate:#EditorCommon.JsonModel.Component.GUI",
          "classname": "ImageView",
          "name": "logo",
          "ZOrder": 0,
          "actiontag": 66610962,
          "anchorPointX": 0.5,
          "anchorPointY": 0.5,
          "classType": "CocoStudio.EngineAdapterWrap.CSImageView",
          "colorB": 255,
          "colorG": 255,
          "colorR": 255,
          "customProperty": "",
          "flipX": false,
          "flipY": false,
          "height": 311,
          "ignoreSize": true,
          "layoutParameter": null,
          "opacity": 255,
          "positionPercentX": 0.5,
          "positionPercentY": 0.75,
          "positionType": 0,
          "rotation": 0,
          "scaleX": 1,
          "scaleY": 1,
          "sizePercentX": 0.9765625,
          "sizePercentY": 0.323958337,
          "sizeType": 0,
          "tag": 455,
          "touchAble": false,
          "useMergedTexture": true,
          "visible": true,
          "width": 625,
          "x": 320,
          "y": 720,
          "capInsetsHeight": 1,
          "capInsetsWidth": 1,
          "capInsetsX": 0,
          "capInsetsY": 0,
          "fileName": null,
          "fileNameData": {
            "path": "logo1.png",
            "plistFile": "",
            "resourceType": 1
          },
          "scale9Enable": false,
          "scale9Height": 311,
          "scale9Width": 625
        }
      },
      {
        "classname": "Button",
        "name": null,
        "children": [],
        "options": {
          "__type": "ButtonSurrogate:#EditorCommon.JsonModel.Component.GUI",
          "classname": "Button",
          "name": "play_button",
          "ZOrder": 0,
          "actiontag": 3038051,
          "anchorPointX": 0.5,
          "anchorPointY": 0.5,
          "classType": "CocoStudio.EngineAdapterWrap.CSButton",
          "colorB": 255,
          "colorG": 255,
          "colorR": 255,
          "customProperty": "",
          "flipX": false,
          "flipY": false,
          "height": 159,
          "ignoreSize": true,
          "layoutParameter": null,
          "opacity": 255,
          "positionPercentX": 0.5,
          "positionPercentY": 0.134899065,
          "positionType": 0,
          "rotation": 0,
          "scaleX": 1,
          "scaleY": 1,
          "sizePercentX": 0.2578125,
          "sizePercentY": 0.165625,
          "sizeType": 0,
          "tag": 456,
          "touchAble": true,
          "useMergedTexture": true,
          "visible": true,
          "width": 165,
          "x": 320,
          "y": 129,
          "capInsetsHeight": 1,
          "capInsetsWidth": 1,
          "capInsetsX": 0,
          "capInsetsY": 0,
          "disabled": null,
          "disabledData": {
            "path": "play_button_press.png",
            "plistFile": "",
            "resourceType": 1
          },
          "fontName": "微软雅黑",
          "fontSize": 14,
          "fontType": 0,
          "normal": null,
          "normalData": {
            "path": "play_button_normal.png",
            "plistFile": "",
            "resourceType": 1
          },
          "pressed": null,
          "pressedData": {
            "path": "play_button_press.png",
            "plistFile": "",
            "resourceType": 1
          },
          "scale9Enable": false,
          "scale9Height": 159,
          "scale9Width": 165,
          "text": "",
          "textColorB": 255,
          "textColorG": 255,
          "textColorR": 255
        }
      },
      {
        "classname": "Button",
        "name": null,
        "children": [],
        "options": {
          "__type": "ButtonSurrogate:#EditorCommon.JsonModel.Component.GUI",
          "classname": "Button",
          "name": "settings_button",
          "ZOrder": 0,
          "actiontag": 421720,
          "anchorPointX": 0.5,
          "anchorPointY": 0.5,
          "classType": "CocoStudio.EngineAdapterWrap.CSButton",
          "colorB": 255,
          "colorG": 255,
          "colorR": 255,
          "customProperty": "",
          "flipX": false,
          "flipY": false,
          "height": 70,
          "ignoreSize": true,
          "layoutParameter": null,
          "opacity": 255,
          "positionPercentX": 0.099928,
          "positionPercentY": 0.0615803041,
          "positionType": 0,
          "rotation": 0,
          "scaleX": 1,
          "scaleY": 1,
          "sizePercentX": 0.1125,
          "sizePercentY": 0.0729166642,
          "sizeType": 0,
          "tag": 457,
          "touchAble": true,
          "useMergedTexture": true,
          "visible": true,
          "width": 72,
          "x": 63,
          "y": 59,
          "capInsetsHeight": 1,
          "capInsetsWidth": 1,
          "capInsetsX": 0,
          "capInsetsY": 0,
          "disabled": null,
          "disabledData": {
            "path": "mm_config_press.png",
            "plistFile": "",
            "resourceType": 1
          },
          "fontName": "微软雅黑",
          "fontSize": 14,
          "fontType": 0,
          "normal": null,
          "normalData": {
            "path": "mm_config_normal.png",
            "plistFile": "",
            "resourceType": 1
          },
          "pressed": null,
          "pressedData": {
            "path": "mm_config_press.png",
            "plistFile": "",
            "resourceType": 1
          },
          "scale9Enable": false,
          "scale9Height": 70,
          "scale9Width": 72,
          "text": "",
          "textColorB": 255,
          "textColorG": 255,
          "textColorR": 255
        }
      }
    ],
    "options": {
      "__type": "PanelSurrogate:#EditorCommon.JsonModel.Component.GUI",
      "classname": "Panel",
      "name": "panel",
      "ZOrder": 0,
      "actiontag": -1,
      "anchorPointX": 0,
      "anchorPointY": 0,
      "classType": "CocoStudio.EngineAdapterWrap.CSPanel",
      "colorB": 255,
      "colorG": 255,
      "colorR": 255,
      "customProperty": "",
      "flipX": false,
      "flipY": false,
      "height": 960,
      "ignoreSize": false,
      "layoutParameter": null,
      "opacity": 255,
      "positionPercentX": 0,
      "positionPercentY": 0,
      "positionType": 0,
      "rotation": 0,
      "scaleX": 1,
      "scaleY": 1,
      "sizePercentX": 1,
      "sizePercentY": 1,
      "sizeType": 0,
      "tag": 454,
      "touchAble": true,
      "useMergedTexture": true,
      "visible": true,
      "width": 640,
      "x": 0,
      "y": 0,
      "adaptScreen": false,
      "backGroundImage": null,
      "backGroundImageData": null,
      "backGroundScale9Enable": false,
      "bgColorB": 255,
      "bgColorG": 200,
      "bgColorOpacity": 0,
      "bgColorR": 150,
      "bgEndColorB": 255,
      "bgEndColorG": 200,
      "bgEndColorR": 150,
      "bgStartColorB": 255,
      "bgStartColorG": 255,
      "bgStartColorR": 255,
      "capInsetsHeight": 1,
      "capInsetsWidth": 1,
      "capInsetsX": 0,
      "capInsetsY": 0,
      "clipAble": false,
      "colorType": 1,
      "layoutType": 0,
      "vectorX": 0,
      "vectorY": -0.5
    }
  }
}