{
  "companyName": "IppoGames",
  "productName": "Make Pop Corn",
  "productVersion": "0.2",
  "dataUrl": "POP.data.unityweb",
  "wasmCodeUrl": "POP.wasm",
  "wasmFrameworkUrl": "POP.wasm.framework.unityweb",
  "graphicsAPI": [
    "WebGL 2.0",
    "WebGL 1.0"
  ],
  "webglContextAttributes": {
    "preserveDrawingBuffer": false
  },
  "splashScreenStyle": "Light",
  "backgroundColor": "#F180FF",
  "cacheControl": {
    "default": "must-revalidate"
  },
  "developmentBuild": false,
  "multithreading": false,
  "unityVersion": "2019.3.10f1"
}